{
  "date_id": "2023-11-22",
  "level_to_district_to_dsds": {
    "1": {
      "LK-81": [
        "LK-8121",
        "LK-8130",
        "LK-8136",
        "LK-8142"
      ],
      "LK-12": [
        "LK-1227"
      ],
      "LK-33": [
        "LK-3325"
      ],
      "LK-21": [
        "LK-2112",
        "LK-2118",
        "LK-2148",
        "LK-2151"
      ],
      "LK-92": [
        "LK-9203",
        "LK-9230"
      ],
      "LK-61": [
        "LK-6163",
        "LK-6187"
      ],
      "LK-22": [
        "LK-2233"
      ],
      "LK-32": [
        "LK-3206",
        "LK-3212"
      ],
      "LK-23": [
        "LK-2303"
      ],
      "LK-91": [
        "LK-9109",
        "LK-9124",
        "LK-9130",
        "LK-9136",
        "LK-9139"
      ]
    },
    "2": {
      "LK-81": [
        "LK-8124",
        "LK-8139"
      ],
      "LK-21": [
        "LK-2103",
        "LK-2139",
        "LK-2142",
        "LK-2154",
        "LK-2154",
        "LK-2157"
      ],
      "LK-92": [
        "LK-9206",
        "LK-9209",
        "LK-9212",
        "LK-9215",
        "LK-9218",
        "LK-9221",
        "LK-9224",
        "LK-9227"
      ],
      "LK-32": [
        "LK-3209"
      ],
      "LK-91": [
        "LK-9103",
        "LK-9106",
        "LK-9112",
        "LK-9127",
        "LK-9133",
        "LK-9142"
      ]
    },
    "3": {
      "LK-81": [
        "LK-8118"
      ],
      "LK-91": [
        "LK-9115",
        "LK-9118",
        "LK-9121",
        "LK-9145",
        "LK-9151"
      ]
    }
  }
}